MANIFEST.in
README.md
setup.py
Pom/LICENSE.txt
Pom/__init__.py
Pom/main.py
Pom/app/Introduction.py
Pom/app/__init__.py
Pom/app/pages/2_Results_table.py
Pom/app/pages/3_Gallery.py
Pom/app/pages/4_Browse tomograms.py
Pom/app/pages/5_Particle_picking.py
Pom/app/pages/6_Template_matching.py
Pom/app/pages/__init__.py
Pom/core/__init__.py
Pom/core/cli_fn.py
Pom/core/config.py
Pom/core/opengl_classes.py
Pom/core/project_configuration.json
Pom/core/render.py
Pom/core/render_configuration.json
Pom/core/util.py
Pom/models/__init__.py
Pom/models/phase1model.py
Pom/models/phase2model.py
Pom/shaders/__init__.py
Pom/shaders/ndc_image.glsl
Pom/shaders/raytrace_volume.glsl
Pom/shaders/se_depth_edge_detect.glsl
Pom/shaders/se_depth_mask_shader.glsl
Pom/shaders/se_surface_model_shader.glsl
Pom_cryoET.egg-info/PKG-INFO
Pom_cryoET.egg-info/SOURCES.txt
Pom_cryoET.egg-info/dependency_links.txt
Pom_cryoET.egg-info/entry_points.txt
Pom_cryoET.egg-info/requires.txt
Pom_cryoET.egg-info/top_level.txt