Metadata-Version: 2.1
Name: Pom-cryoET
Version: 1.1.0
Author: mgflast
Author-email: m.g.f.last@lumc.nl
License: GPL v3
Requires-Dist: Ais-cryoET>=1.0.41
Requires-Dist: matplotlib
Requires-Dist: openpyxl
Requires-Dist: pandas
Requires-Dist: streamlit
Requires-Dist: streamlit-aggrid
Requires-Dist: Pommie
